README.md
setup.py
cms_extensions/__init__.py
cms_extensions/admin.py
cms_extensions/app_settings.py
cms_extensions/cms_toolbars.py
cms_extensions/models.py
cms_extensions/utils.py
cms_extensions/management/__init__.py
django_cms_extensions.egg-info/PKG-INFO
django_cms_extensions.egg-info/SOURCES.txt
django_cms_extensions.egg-info/dependency_links.txt
django_cms_extensions.egg-info/not-zip-safe
django_cms_extensions.egg-info/top_level.txt