Metadata-Version: 1.0
Name: django-cms-extensions
Version: 0.2
Summary: Useful extensions for Django CMS
Home-page: https://github.com/pengutronix/django-cms-extensions
Author: Florian Scherf
Author-email: f.scherf@pengutronix.de
License: BSD
Platform: UNKNOWN
